dst_server_deploy/__init__.py
dst_server_deploy/cave.py
dst_server_deploy/docker_composer.py
dst_server_deploy/forest.py
dst_server_deploy/helpers.py
dst_server_deploy/server.py
dst_server_deploy/data/__init__.py
dst_server_deploy/data/presets.py
dst_server_deploy-1.0.0.data/scripts/dst-server-deploy
dst_server_deploy-1.0.0.dist-info/DESCRIPTION.rst
dst_server_deploy-1.0.0.dist-info/METADATA
dst_server_deploy-1.0.0.dist-info/RECORD
dst_server_deploy-1.0.0.dist-info/WHEEL
dst_server_deploy-1.0.0.dist-info/metadata.json
dst_server_deploy-1.0.0.dist-info/top_level.txt
