Metadata-Version: 2.0
Name: dst-server-deploy
Version: 1.0.0
Summary: Generate files to deploy a Don't Starve Together Server Docker Container.
Home-page: https://gitlab.com/lego_engineer/dst-server-deploy
Author: lego_engineer
Author-email: protopeters@gmail.com
License: MIT
Keywords: DST dont starve together server docker docker-compose
Platform: UNKNOWN
Classifier: Development Status :: 4 - Beta
Classifier: License :: OSI Approved :: MIT License
Classifier: Programming Language :: Python :: 3.5
Classifier: Topic :: Games/Entertainment :: Role-Playing
Requires-Dist: pyyaml
